qrlew_datasets/__init__.py
qrlew_datasets/build.py
qrlew_datasets/database.py
qrlew_datasets/databases/__init__.py
qrlew_datasets/databases/mariadb.py
qrlew_datasets/databases/postgresql.py
qrlew_datasets/files.py
qrlew_datasets/network.py
qrlew_datasets/sources.py
qrlew_datasets-0.9.0.dist-info/LICENSE
qrlew_datasets-0.9.0.dist-info/METADATA
qrlew_datasets-0.9.0.dist-info/WHEEL
qrlew_datasets-0.9.0.dist-info/RECORD
