Metadata-Version: 2.1
Name: qrlew-datasets
Version: 0.9.0
Summary: Sample SQL datasets
License: Apache 2.0
Author: Nicolas Grislain
Author-email: ng@sarus.tech
Requires-Python: >=3.9,<4.0
Classifier: License :: Other/Proprietary License
Classifier: Programming Language :: Python :: 3
Classifier: Programming Language :: Python :: 3.9
Classifier: Programming Language :: Python :: 3.10
Classifier: Programming Language :: Python :: 3.11
Classifier: Programming Language :: Python :: 3.12
Requires-Dist: psycopg2 (<3.0)
Requires-Dist: pymysql (>=1.1.0,<2.0.0)
Requires-Dist: sqlalchemy (>=2.0,<3.0)
Requires-Dist: termcolor (>=2.3.0,<3.0.0)
